as3lib/__init__.py
as3lib/configmodule.py
as3lib/initconfig.py
as3lib/interface_tk.py
as3lib/keyConversions.py
as3lib/parser.py
as3lib/toplevel.py
as3lib/com/__init__.py
as3lib/com/adobe.py
as3lib/flash/__init__.py
as3lib/flash/crypto.py
as3lib/flash/display.py
as3lib/flash/display3D.py
as3lib/flash/errors.py
as3lib/flash/events.py
as3lib/flash/filesystem.py
as3lib/flash/net.py
as3lib/flash/system.py
as3lib/flash/ui.py
as3lib/flash/utils.py
as3lib-0.0.8.dist-info/LICENSE
as3lib-0.0.8.dist-info/METADATA
as3lib-0.0.8.dist-info/WHEEL
as3lib-0.0.8.dist-info/top_level.txt
as3lib-0.0.8.dist-info/RECORD
