Metadata-Version: 2.1
Name: as3lib
Version: 0.0.8
Summary: Python implementation of ActionScript3
Home-page: https://github.com/ajdelguidice/python-as3lib
Author: ajdelguidice
Author-email: ajdelguidice@gmail.com
Classifier: Development Status :: 4 - Beta
Classifier: License :: OSI Approved :: MIT License
Classifier: Operating System :: OS Independent
Classifier: Programming Language :: Python :: 3.10
Classifier: Topic :: Utilities
Requires-Python: >=3.10
License-File: LICENSE
Requires-Dist: numpy
Requires-Dist: tkhtmlview
Requires-Dist: Pillow
